jjava/__init__.py
jjava/_version.py
jjava-1.0a6.data/data/share/jupyter/kernels/java/jjava-launcher.jar
jjava-1.0a6.data/data/share/jupyter/kernels/java/jjava.jar
jjava-1.0a6.data/data/share/jupyter/kernels/java/kernel.json
jjava-1.0a6.dist-info/licenses/LICENSE
jjava-1.0a6.dist-info/licenses/NOTICE.txt
jjava-1.0a6.dist-info/METADATA
jjava-1.0a6.dist-info/WHEEL
jjava-1.0a6.dist-info/top_level.txt
jjava-1.0a6.dist-info/RECORD
