Metadata-Version: 2.4
Name: jjava
Version: 1.0a6
Summary: A Jupyter kernel for Java notebooks
Author-email: Andrus Adamchik <andrus@objectstyle.com>
License:                                  Apache License
Project-URL: Documentation, https://dflib.org/jjava/docs/1.x/
Project-URL: Repository, https://github.com/dflib/jjava
Project-URL: Download, https://github.com/dflib/jjava/releases
Project-URL: Issues, https://github.com/dflib/jjava/issues
Project-URL: Changelog, https://github.com/dflib/jjava/blob/main/RELEASE-NOTES.md
Keywords: windows,macos,linux,jupyter,java,jupyter-kernels,pip
Classifier: Programming Language :: Python :: 3
Classifier: Programming Language :: Java
Classifier: License :: OSI Approved :: MIT License
Classifier: Operating System :: MacOS
Classifier: Operating System :: POSIX :: Linux
Classifier: Operating System :: Microsoft :: Windows
Requires-Python: >=3.8
License-File: LICENSE
License-File: NOTICE.txt
Dynamic: license-file
